README
__init__.py
lib.py
pyromsgui.py
setup.py
pyromsgui.egg-info/PKG-INFO
pyromsgui.egg-info/SOURCES.txt
pyromsgui.egg-info/dependency_links.txt
pyromsgui.egg-info/requires.txt
pyromsgui.egg-info/top_level.txt