Metadata-Version: 1.1
Name: pyromsgui
Version: 0.1.0
Summary: GUI to visualize ROMS files
Home-page: https://github.com/rsoutelino/pyromsgui/
Author: Rafael Soutelino
Author-email: rsoutelino@gmail.com
License: UNKNOWN
Download-URL: https://github.com/rsoutelino/pyromsgui/
Keywords: oceanography,ocean modeling,roms
Platform: any
Classifier: Development Status :: 3 - Alpha
Classifier: Environment :: X11 Applications
Classifier: Intended Audience :: Science/Research
Classifier: License :: OSI Approved :: MIT License
Classifier: Operating System :: OS Independent
Classifier: Programming Language :: Python
Classifier: Topic :: Scientific/Engineering
